kaki/__init__.py
kaki/app.py
kaki-0.1.9.dist-info/METADATA
kaki-0.1.9.dist-info/WHEEL
kaki-0.1.9.dist-info/top_level.txt
kaki-0.1.9.dist-info/RECORD
