Metadata-Version: 2.1
Name: kaki
Version: 0.1.9
Summary: Kivy application library on steroids
Home-page: https://github.com/tito/kaki
Author: Mathieu Virbel
Author-email: mat@meltingrocks.com
Project-URL: Bug Reports, https://github.com/tito/kaki/issues
Project-URL: Source, https://github.com/tito/kaki/
Classifier: Development Status :: 4 - Beta
Classifier: Intended Audience :: Developers
Classifier: Topic :: Software Development :: Build Tools
Classifier: License :: OSI Approved :: MIT License
Classifier: Programming Language :: Python :: 3
Classifier: Programming Language :: Python :: 3.5
Classifier: Programming Language :: Python :: 3.6
Classifier: Programming Language :: Python :: 3.7
Classifier: Programming Language :: Python :: 3.8
Classifier: Programming Language :: Python :: 3.9
Classifier: Programming Language :: Python :: 3.10
Classifier: Programming Language :: Python :: 3.11
